pygraphsearch/__init__.py
pygraphsearch/algorithm.py
pygraphsearch/edge.py
pygraphsearch/frontier.py
pygraphsearch/frontiers/__init__.py
pygraphsearch/frontiers/a_star_frontier.py
pygraphsearch/frontiers/breadth_first_frontier.py
pygraphsearch/frontiers/depth_first_frontier.py
pygraphsearch/frontiers/dijkstra_frontier.py
pygraphsearch/frontiers/iterative_deepening_frontier.py
pygraphsearch/node.py
pygraphsearch/path.py
pygraphsearch/py.typed
pygraphsearch/search.py
pygraphsearch/state.py
pygraphsearch-3.0.0.dist-info/WHEEL
pygraphsearch-3.0.0.dist-info/METADATA
pygraphsearch-3.0.0.dist-info/RECORD
