Metadata-Version: 2.1
Name: pygraphsearch
Version: 3.0.0
Summary: A python package to search graphs.
Home-page: https://github.com/abrahammurciano/pygraphsearch
License: MIT
Author: Abraham Murciano
Author-email: abrahammurciano@gmail.com
Requires-Python: >=3.10,<4.0
Classifier: License :: OSI Approved :: MIT License
Classifier: Programming Language :: Python :: 3
Classifier: Programming Language :: Python :: 3.10
Requires-Dist: typed-data-structures (>=0.0.2,<0.0.3)
Project-URL: Repository, https://github.com/abrahammurciano/pygraphsearch
